fast_hdbscan/__init__.py
fast_hdbscan/boruvka.py
fast_hdbscan/branches.py
fast_hdbscan/cluster_trees.py
fast_hdbscan/core_graph.py
fast_hdbscan/disjoint_set.py
fast_hdbscan/hdbscan.py
fast_hdbscan/numba_kdtree.py
fast_hdbscan/sub_clusters.py
fast_hdbscan-0.2.2.dist-info/LICENSE
fast_hdbscan-0.2.2.dist-info/METADATA
fast_hdbscan-0.2.2.dist-info/WHEEL
fast_hdbscan-0.2.2.dist-info/top_level.txt
fast_hdbscan-0.2.2.dist-info/RECORD
