Metadata-Version: 2.1
Name: fast-hdbscan
Version: 0.2.2
Summary: A fast multicore version of hdbscan for low dimensional euclidean spaces
Home-page: https://github.com/TutteInstitute/fast_hdbscan
Author: Leland McInnes
Author-email: leland.mcinnes@gmail.com
Maintainer: Leland McInnes
Maintainer-email: leland.mcinnes@gmail.com
License: BSD 2-Clause License
Keywords: cluster,clustering,hdbscan,dbscan
Classifier: License :: OSI Approved :: BSD License
Classifier: Programming Language :: Python :: 3.9
Classifier: Programming Language :: Python :: 3.10
Classifier: Programming Language :: Python :: 3.11
Classifier: Programming Language :: Python :: 3.12
Classifier: Development Status :: 4 - Beta
Classifier: Operating System :: OS Independent
Requires-Python: >=3.9
License-File: LICENSE
Requires-Dist: numpy>=1.21
Requires-Dist: numba>=0.56
Requires-Dist: scikit-learn>=1.6
